Charisma_toolbox-0.0.2-py3.8-nspkg.pth
Charisma_toolbox-0.0.2.data/data/help/orange3-example/.buildinfo
Charisma_toolbox-0.0.2.data/data/help/orange3-example/genindex.html
Charisma_toolbox-0.0.2.data/data/help/orange3-example/index.html
Charisma_toolbox-0.0.2.data/data/help/orange3-example/objects.inv
Charisma_toolbox-0.0.2.data/data/help/orange3-example/search.html
Charisma_toolbox-0.0.2.data/data/help/orange3-example/searchindex.js
Charisma_toolbox-0.0.2.data/data/help/orange3-example/_images/LDAconf.png
Charisma_toolbox-0.0.2.data/data/help/orange3-example/_images/LDAcve.png
Charisma_toolbox-0.0.2.data/data/help/orange3-example/_images/LDAscatter.png
Charisma_toolbox-0.0.2.data/data/help/orange3-example/_images/PCAQTplot.png
Charisma_toolbox-0.0.2.data/data/help/orange3-example/_images/PCAexample.png
Charisma_toolbox-0.0.2.data/data/help/orange3-example/_images/PCAexplVar.png
Charisma_toolbox-0.0.2.data/data/help/orange3-example/_images/PCArmsec.png
Charisma_toolbox-0.0.2.data/data/help/orange3-example/_images/TestAndScore.png
Charisma_toolbox-0.0.2.data/data/help/orange3-example/_images/TestAndScoreCopy.png
Charisma_toolbox-0.0.2.data/data/help/orange3-example/_images/mywidget.png
Charisma_toolbox-0.0.2.data/data/help/orange3-example/_sources/index.rst.txt
Charisma_toolbox-0.0.2.data/data/help/orange3-example/_sources/widgets/OWLDA.rst.txt
Charisma_toolbox-0.0.2.data/data/help/orange3-example/_sources/widgets/OWPCALDA.rst.txt
Charisma_toolbox-0.0.2.data/data/help/orange3-example/_sources/widgets/OWPLSRegression.rst.txt
Charisma_toolbox-0.0.2.data/data/help/orange3-example/_sources/widgets/OWpcaAKWeller.rst.txt
Charisma_toolbox-0.0.2.data/data/help/orange3-example/_sources/widgets/OWtestandscoreAKWeller.rst.txt
Charisma_toolbox-0.0.2.data/data/help/orange3-example/_static/basic.css
Charisma_toolbox-0.0.2.data/data/help/orange3-example/_static/doctools.js
Charisma_toolbox-0.0.2.data/data/help/orange3-example/_static/documentation_options.js
Charisma_toolbox-0.0.2.dist-info/LICENSE
Charisma_toolbox-0.0.2.dist-info/LICENSE.txt
Charisma_toolbox-0.0.2.dist-info/METADATA
Charisma_toolbox-0.0.2.dist-info/WHEEL
Charisma_toolbox-0.0.2.dist-info/entry_points.txt
Charisma_toolbox-0.0.2.dist-info/namespace_packages.txt
Charisma_toolbox-0.0.2.dist-info/top_level.txt
Charisma_toolbox-0.0.2.dist-info/RECORD
