Metadata-Version: 2.1
Name: Charisma-toolbox
Version: 0.0.2
Summary: Add-ons providing tools for chemometric data analysis
Home-page: UNKNOWN
Author: UNKNOWN
Author-email: UNKNOWN
License: UNKNOWN
Keywords: orange3 add-on
Platform: UNKNOWN
Requires-Dist: Orange3
